typed_envs__mypyc.cp312-win32.pyd
typed_envs/ENVIRONMENT_VARIABLES.cp312-win32.pyd
typed_envs/ENVIRONMENT_VARIABLES.py
typed_envs/__init__.cp312-win32.pyd
typed_envs/__init__.py
typed_envs/_env_var.py
typed_envs/_typed.cp312-win32.pyd
typed_envs/_typed.py
typed_envs/factory.py
typed_envs/mypy_plugin.py
typed_envs/py.typed
typed_envs/registry.cp312-win32.pyd
typed_envs/registry.py
typed_envs/typing.cp312-win32.pyd
typed_envs/typing.py
typed_envs-0.2.4.dist-info/METADATA
typed_envs-0.2.4.dist-info/WHEEL
typed_envs-0.2.4.dist-info/top_level.txt
typed_envs-0.2.4.dist-info/RECORD
